pywebber/__init__.py
pywebber/indexing.py
pywebber/lorem.py
pywebber/ripper.py
pywebber/test.py
pywebber/utils.py
pywebber-5.0.dist-info/METADATA
pywebber-5.0.dist-info/RECORD
pywebber-5.0.dist-info/WHEEL
pywebber-5.0.dist-info/top_level.txt
