Metadata-Version: 2.1
Name: pywebber
Version: 5.0
Summary: Common tools employed in web development
Home-page: https://github.com/immensity/pywebber
Author: Chidi Matthew Orji
Author-email: orjichidi95@gmail.com
License: MIT
Download-URL: https://codeload.github.com/immensity/pywebber/zip/master
Keywords: web crawler,lorem ipsum text generator,page indexer
Platform: UNKNOWN
Classifier: Development Status :: 5 - Production/Stable
Classifier: Environment :: Web Environment
Classifier: Programming Language :: Python :: 3.6
Classifier: License :: OSI Approved :: MIT License
Classifier: Intended Audience :: Developers
Classifier: Environment :: Web Environment
Classifier: Topic :: Internet :: WWW/HTTP :: Browsers
Requires-Dist: beautifulsoup4 (==4.6.0)
Requires-Dist: requests (==2.18.4)
